django_infranil-1.1.0.dist-info/DESCRIPTION.rst
django_infranil-1.1.0.dist-info/METADATA
django_infranil-1.1.0.dist-info/RECORD
django_infranil-1.1.0.dist-info/WHEEL
django_infranil-1.1.0.dist-info/metadata.json
django_infranil-1.1.0.dist-info/top_level.txt
infranil/__init__.py
infranil/models.py
infranil/urls.py
infranil/views.py
