Metadata-Version: 2.0
Name: django-infranil
Version: 1.1.0
Summary: almost flat pages
Home-page: https://github.com/ccnmtl/django-infranil
Author: Anders Pearson
Author-email: anders@columbia.edu
License: BSD
Platform: any
Requires-Dist: Django
